[
  {"path":"people/2/profile.html","size":1014,"last_commit":"de382cdc7e3cae92795dc0760cf8efd2ac6a38fe","last_date":"2026-06-07T18:53:28+02:00","last_author":"Shaun Roselt"},
  {"path":"people/2/data/profile.html","size":1256,"last_commit":"e7fa1ef7535c303059cb5490e5db33e40380fbfe","last_date":"2026-06-06T00:59:14+02:00","last_author":"Shaun Roselt"},
  {"path":"people/2/data/tree.html","size":69,"last_commit":"8c820135e5f98c014c3de475ad4c16a03aa0233c","last_date":"2026-06-04T00:29:28+02:00","last_author":"Shaun Roselt"},
  {"path":"people/2/data/talk.html","size":67,"last_commit":"8c820135e5f98c014c3de475ad4c16a03aa0233c","last_date":"2026-06-04T00:29:28+02:00","last_author":"Shaun Roselt"},
  {"path":"people/2/data/changes.html","size":367,"last_commit":"8c820135e5f98c014c3de475ad4c16a03aa0233c","last_date":"2026-06-04T00:29:28+02:00","last_author":"Shaun Roselt"},
  {"path":"people/2/data/media.html","size":70,"last_commit":"8c820135e5f98c014c3de475ad4c16a03aa0233c","last_date":"2026-06-04T00:29:28+02:00","last_author":"Shaun Roselt"},
  {"path":"people/15/profile.html","size":1010,"last_commit":"de382cdc7e3cae92795dc0760cf8efd2ac6a38fe","last_date":"2026-06-07T18:53:28+02:00","last_author":"Shaun Roselt"},
  {"path":"people/15/data/profile.html","size":11725,"last_commit":"b56c7c69bf3f8e0b023e91b853e14e2e44db9d49","last_date":"2026-06-04T12:39:21+02:00","last_author":"Shaun Roselt"},
  {"path":"people/15/data/tree.html","size":69,"last_commit":"6af1a2a5fb61bc9ea7f0be9f7536a4e8c53fd64c","last_date":"2026-06-04T00:29:28+02:00","last_author":"Shaun Roselt"},
  {"path":"people/15/data/talk.html","size":67,"last_commit":"6af1a2a5fb61bc9ea7f0be9f7536a4e8c53fd64c","last_date":"2026-06-04T00:29:28+02:00","last_author":"Shaun Roselt"},
  {"path":"people/15/data/profile-table.html","size":1783,"last_commit":"b56c7c69bf3f8e0b023e91b853e14e2e44db9d49","last_date":"2026-06-04T12:39:21+02:00","last_author":"Shaun Roselt"},
  {"path":"people/15/data/changes.html","size":367,"last_commit":"6af1a2a5fb61bc9ea7f0be9f7536a4e8c53fd64c","last_date":"2026-06-04T00:29:28+02:00","last_author":"Shaun Roselt"},
  {"path":"people/15/data/media.html","size":70,"last_commit":"6af1a2a5fb61bc9ea7f0be9f7536a4e8c53fd64c","last_date":"2026-06-04T00:29:28+02:00","last_author":"Shaun Roselt"},
  {"path":"people/21/profile.html","size":1024,"last_commit":"de382cdc7e3cae92795dc0760cf8efd2ac6a38fe","last_date":"2026-06-07T18:53:28+02:00","last_author":"Shaun Roselt"},
  {"path":"people/21/data/profile.html","size":862,"last_commit":"e7fa1ef7535c303059cb5490e5db33e40380fbfe","last_date":"2026-06-06T00:59:14+02:00","last_author":"Shaun Roselt"},
  {"path":"people/21/data/tree.html","size":69,"last_commit":"b56c7c69bf3f8e0b023e91b853e14e2e44db9d49","last_date":"2026-06-04T12:39:21+02:00","last_author":"Shaun Roselt"},
  {"path":"people/21/data/talk.html","size":67,"last_commit":"b56c7c69bf3f8e0b023e91b853e14e2e44db9d49","last_date":"2026-06-04T12:39:21+02:00","last_author":"Shaun Roselt"},
  {"path":"people/21/data/changes.html","size":124,"last_commit":"b56c7c69bf3f8e0b023e91b853e14e2e44db9d49","last_date":"2026-06-04T12:39:21+02:00","last_author":"Shaun Roselt"},
  {"path":"people/21/data/media.html","size":70,"last_commit":"b56c7c69bf3f8e0b023e91b853e14e2e44db9d49","last_date":"2026-06-04T12:39:21+02:00","last_author":"Shaun Roselt"},
  {"path":"people/9/profile.html","size":1015,"last_commit":"de382cdc7e3cae92795dc0760cf8efd2ac6a38fe","last_date":"2026-06-07T18:53:28+02:00","last_author":"Shaun Roselt"},
  {"path":"people/9/data/profile.html","size":1331,"last_commit":"d8a9adb58da2f3a8c8002cccb2944c0423fc9c3e","last_date":"2026-06-07T16:00:57+02:00","last_author":"Shaun Roselt"},
  {"path":"people/9/data/tree.html","size":69,"last_commit":"d8a9adb58da2f3a8c8002cccb2944c0423fc9c3e","last_date":"2026-06-07T16:00:57+02:00","last_author":"Shaun Roselt"},
  {"path":"people/9/data/talk.html","size":67,"last_commit":"d8a9adb58da2f3a8c8002cccb2944c0423fc9c3e","last_date":"2026-06-07T16:00:57+02:00","last_author":"Shaun Roselt"},
  {"path":"people/9/data/changes.html","size":367,"last_commit":"d8a9adb58da2f3a8c8002cccb2944c0423fc9c3e","last_date":"2026-06-07T16:00:57+02:00","last_author":"Shaun Roselt"},
  {"path":"people/9/data/media.html","size":70,"last_commit":"d8a9adb58da2f3a8c8002cccb2944c0423fc9c3e","last_date":"2026-06-07T16:00:57+02:00","last_author":"Shaun Roselt"},
  {"path":"people/4/profile.html","size":1015,"last_commit":"de382cdc7e3cae92795dc0760cf8efd2ac6a38fe","last_date":"2026-06-07T18:53:28+02:00","last_author":"Shaun Roselt"},
  {"path":"people/4/data/profile.html","size":1331,"last_commit":"d8a9adb58da2f3a8c8002cccb2944c0423fc9c3e","last_date":"2026-06-07T16:00:57+02:00","last_author":"Shaun Roselt"},
  {"path":"people/4/data/tree.html","size":69,"last_commit":"d8a9adb58da2f3a8c8002cccb2944c0423fc9c3e","last_date":"2026-06-07T16:00:57+02:00","last_author":"Shaun Roselt"},
  {"path":"people/4/data/talk.html","size":67,"last_commit":"d8a9adb58da2f3a8c8002cccb2944c0423fc9c3e","last_date":"2026-06-07T16:00:57+02:00","last_author":"Shaun Roselt"},
  {"path":"people/4/data/changes.html","size":367,"last_commit":"d8a9adb58da2f3a8c8002cccb2944c0423fc9c3e","last_date":"2026-06-07T16:00:57+02:00","last_author":"Shaun Roselt"},
  {"path":"people/4/data/media.html","size":70,"last_commit":"d8a9adb58da2f3a8c8002cccb2944c0423fc9c3e","last_date":"2026-06-07T16:00:57+02:00","last_author":"Shaun Roselt"},
  {"path":"people/17/profile.html","size":1033,"last_commit":"de382cdc7e3cae92795dc0760cf8efd2ac6a38fe","last_date":"2026-06-07T18:53:28+02:00","last_author":"Shaun Roselt"},
  {"path":"people/17/data/profile.html","size":1189,"last_commit":"e7fa1ef7535c303059cb5490e5db33e40380fbfe","last_date":"2026-06-06T00:59:14+02:00","last_author":"Shaun Roselt"},
  {"path":"people/17/data/tree.html","size":69,"last_commit":"b56c7c69bf3f8e0b023e91b853e14e2e44db9d49","last_date":"2026-06-04T12:39:21+02:00","last_author":"Shaun Roselt"},
  {"path":"people/17/data/talk.html","size":67,"last_commit":"b56c7c69bf3f8e0b023e91b853e14e2e44db9d49","last_date":"2026-06-04T12:39:21+02:00","last_author":"Shaun Roselt"},
  {"path":"people/17/data/changes.html","size":124,"last_commit":"b56c7c69bf3f8e0b023e91b853e14e2e44db9d49","last_date":"2026-06-04T12:39:21+02:00","last_author":"Shaun Roselt"},
  {"path":"people/17/data/media.html","size":70,"last_commit":"b56c7c69bf3f8e0b023e91b853e14e2e44db9d49","last_date":"2026-06-04T12:39:21+02:00","last_author":"Shaun Roselt"},
  {"path":"people/7/profile.html","size":1016,"last_commit":"de382cdc7e3cae92795dc0760cf8efd2ac6a38fe","last_date":"2026-06-07T18:53:28+02:00","last_author":"Shaun Roselt"},
  {"path":"people/7/data/profile.html","size":1333,"last_commit":"07a3081c76e20caf38ae87987328171a644d2571","last_date":"2026-06-07T17:40:16+02:00","last_author":"Shaun Roselt"},
  {"path":"people/7/data/tree.html","size":69,"last_commit":"d8a9adb58da2f3a8c8002cccb2944c0423fc9c3e","last_date":"2026-06-07T16:00:57+02:00","last_author":"Shaun Roselt"},
  {"path":"people/7/data/talk.html","size":67,"last_commit":"d8a9adb58da2f3a8c8002cccb2944c0423fc9c3e","last_date":"2026-06-07T16:00:57+02:00","last_author":"Shaun Roselt"},
  {"path":"people/7/data/changes.html","size":367,"last_commit":"d8a9adb58da2f3a8c8002cccb2944c0423fc9c3e","last_date":"2026-06-07T16:00:57+02:00","last_author":"Shaun Roselt"},
  {"path":"people/7/data/media.html","size":70,"last_commit":"d8a9adb58da2f3a8c8002cccb2944c0423fc9c3e","last_date":"2026-06-07T16:00:57+02:00","last_author":"Shaun Roselt"},
  {"path":"people/16/profile.html","size":1034,"last_commit":"de382cdc7e3cae92795dc0760cf8efd2ac6a38fe","last_date":"2026-06-07T18:53:28+02:00","last_author":"Shaun Roselt"},
  {"path":"people/16/data/profile.html","size":1368,"last_commit":"b56c7c69bf3f8e0b023e91b853e14e2e44db9d49","last_date":"2026-06-04T12:39:21+02:00","last_author":"Shaun Roselt"},
  {"path":"people/16/data/tree.html","size":69,"last_commit":"b56c7c69bf3f8e0b023e91b853e14e2e44db9d49","last_date":"2026-06-04T12:39:21+02:00","last_author":"Shaun Roselt"},
  {"path":"people/16/data/talk.html","size":67,"last_commit":"b56c7c69bf3f8e0b023e91b853e14e2e44db9d49","last_date":"2026-06-04T12:39:21+02:00","last_author":"Shaun Roselt"},
  {"path":"people/16/data/changes.html","size":124,"last_commit":"b56c7c69bf3f8e0b023e91b853e14e2e44db9d49","last_date":"2026-06-04T12:39:21+02:00","last_author":"Shaun Roselt"},
  {"path":"people/16/data/media.html","size":70,"last_commit":"b56c7c69bf3f8e0b023e91b853e14e2e44db9d49","last_date":"2026-06-04T12:39:21+02:00","last_author":"Shaun Roselt"},
  {"path":"people/6/profile.html","size":1017,"last_commit":"de382cdc7e3cae92795dc0760cf8efd2ac6a38fe","last_date":"2026-06-07T18:53:28+02:00","last_author":"Shaun Roselt"},
  {"path":"people/6/data/profile.html","size":1334,"last_commit":"07a3081c76e20caf38ae87987328171a644d2571","last_date":"2026-06-07T17:40:16+02:00","last_author":"Shaun Roselt"},
  {"path":"people/6/data/tree.html","size":69,"last_commit":"d8a9adb58da2f3a8c8002cccb2944c0423fc9c3e","last_date":"2026-06-07T16:00:57+02:00","last_author":"Shaun Roselt"},
  {"path":"people/6/data/talk.html","size":67,"last_commit":"d8a9adb58da2f3a8c8002cccb2944c0423fc9c3e","last_date":"2026-06-07T16:00:57+02:00","last_author":"Shaun Roselt"},
  {"path":"people/6/data/changes.html","size":367,"last_commit":"d8a9adb58da2f3a8c8002cccb2944c0423fc9c3e","last_date":"2026-06-07T16:00:57+02:00","last_author":"Shaun Roselt"},
  {"path":"people/6/data/media.html","size":70,"last_commit":"d8a9adb58da2f3a8c8002cccb2944c0423fc9c3e","last_date":"2026-06-07T16:00:57+02:00","last_author":"Shaun Roselt"},
  {"path":"people/5/profile.html","size":1015,"last_commit":"de382cdc7e3cae92795dc0760cf8efd2ac6a38fe","last_date":"2026-06-07T18:53:28+02:00","last_author":"Shaun Roselt"},
  {"path":"people/5/data/profile.html","size":1331,"last_commit":"d8a9adb58da2f3a8c8002cccb2944c0423fc9c3e","last_date":"2026-06-07T16:00:57+02:00","last_author":"Shaun Roselt"},
  {"path":"people/5/data/tree.html","size":69,"last_commit":"d8a9adb58da2f3a8c8002cccb2944c0423fc9c3e","last_date":"2026-06-07T16:00:57+02:00","last_author":"Shaun Roselt"},
  {"path":"people/5/data/talk.html","size":67,"last_commit":"d8a9adb58da2f3a8c8002cccb2944c0423fc9c3e","last_date":"2026-06-07T16:00:57+02:00","last_author":"Shaun Roselt"},
  {"path":"people/5/data/changes.html","size":367,"last_commit":"d8a9adb58da2f3a8c8002cccb2944c0423fc9c3e","last_date":"2026-06-07T16:00:57+02:00","last_author":"Shaun Roselt"},
  {"path":"people/5/data/media.html","size":70,"last_commit":"d8a9adb58da2f3a8c8002cccb2944c0423fc9c3e","last_date":"2026-06-07T16:00:57+02:00","last_author":"Shaun Roselt"},
  {"path":"people/25/profile.html","size":1027,"last_commit":"de382cdc7e3cae92795dc0760cf8efd2ac6a38fe","last_date":"2026-06-07T18:53:28+02:00","last_author":"Shaun Roselt"},
  {"path":"people/25/data/profile.html","size":1058,"last_commit":"e7fa1ef7535c303059cb5490e5db33e40380fbfe","last_date":"2026-06-06T00:59:14+02:00","last_author":"Shaun Roselt"},
  {"path":"people/25/data/tree.html","size":69,"last_commit":"b56c7c69bf3f8e0b023e91b853e14e2e44db9d49","last_date":"2026-06-04T12:39:21+02:00","last_author":"Shaun Roselt"},
  {"path":"people/25/data/talk.html","size":67,"last_commit":"b56c7c69bf3f8e0b023e91b853e14e2e44db9d49","last_date":"2026-06-04T12:39:21+02:00","last_author":"Shaun Roselt"},
  {"path":"people/25/data/changes.html","size":124,"last_commit":"b56c7c69bf3f8e0b023e91b853e14e2e44db9d49","last_date":"2026-06-04T12:39:21+02:00","last_author":"Shaun Roselt"},
  {"path":"people/25/data/media.html","size":70,"last_commit":"b56c7c69bf3f8e0b023e91b853e14e2e44db9d49","last_date":"2026-06-04T12:39:21+02:00","last_author":"Shaun Roselt"},
  {"path":"people/23/profile.html","size":1015,"last_commit":"de382cdc7e3cae92795dc0760cf8efd2ac6a38fe","last_date":"2026-06-07T18:53:28+02:00","last_author":"Shaun Roselt"},
  {"path":"people/23/data/profile.html","size":859,"last_commit":"e7fa1ef7535c303059cb5490e5db33e40380fbfe","last_date":"2026-06-06T00:59:14+02:00","last_author":"Shaun Roselt"},
  {"path":"people/23/data/tree.html","size":69,"last_commit":"b56c7c69bf3f8e0b023e91b853e14e2e44db9d49","last_date":"2026-06-04T12:39:21+02:00","last_author":"Shaun Roselt"},
  {"path":"people/23/data/talk.html","size":67,"last_commit":"b56c7c69bf3f8e0b023e91b853e14e2e44db9d49","last_date":"2026-06-04T12:39:21+02:00","last_author":"Shaun Roselt"},
  {"path":"people/23/data/changes.html","size":124,"last_commit":"b56c7c69bf3f8e0b023e91b853e14e2e44db9d49","last_date":"2026-06-04T12:39:21+02:00","last_author":"Shaun Roselt"},
  {"path":"people/23/data/media.html","size":70,"last_commit":"b56c7c69bf3f8e0b023e91b853e14e2e44db9d49","last_date":"2026-06-04T12:39:21+02:00","last_author":"Shaun Roselt"},
  {"path":"people/20/profile.html","size":1019,"last_commit":"de382cdc7e3cae92795dc0760cf8efd2ac6a38fe","last_date":"2026-06-07T18:53:28+02:00","last_author":"Shaun Roselt"},
  {"path":"people/20/data/profile.html","size":859,"last_commit":"e7fa1ef7535c303059cb5490e5db33e40380fbfe","last_date":"2026-06-06T00:59:14+02:00","last_author":"Shaun Roselt"},
  {"path":"people/20/data/tree.html","size":69,"last_commit":"b56c7c69bf3f8e0b023e91b853e14e2e44db9d49","last_date":"2026-06-04T12:39:21+02:00","last_author":"Shaun Roselt"},
  {"path":"people/20/data/talk.html","size":67,"last_commit":"b56c7c69bf3f8e0b023e91b853e14e2e44db9d49","last_date":"2026-06-04T12:39:21+02:00","last_author":"Shaun Roselt"},
  {"path":"people/20/data/changes.html","size":124,"last_commit":"b56c7c69bf3f8e0b023e91b853e14e2e44db9d49","last_date":"2026-06-04T12:39:21+02:00","last_author":"Shaun Roselt"},
  {"path":"people/20/data/media.html","size":70,"last_commit":"b56c7c69bf3f8e0b023e91b853e14e2e44db9d49","last_date":"2026-06-04T12:39:21+02:00","last_author":"Shaun Roselt"},
  {"path":"people/3/profile.html","size":1024,"last_commit":"de382cdc7e3cae92795dc0760cf8efd2ac6a38fe","last_date":"2026-06-07T18:53:28+02:00","last_author":"Shaun Roselt"},
  {"path":"people/3/data/profile.html","size":1657,"last_commit":"e7fa1ef7535c303059cb5490e5db33e40380fbfe","last_date":"2026-06-06T00:59:14+02:00","last_author":"Shaun Roselt"},
  {"path":"people/3/data/tree.html","size":69,"last_commit":"8c820135e5f98c014c3de475ad4c16a03aa0233c","last_date":"2026-06-04T00:29:28+02:00","last_author":"Shaun Roselt"},
  {"path":"people/3/data/talk.html","size":67,"last_commit":"8c820135e5f98c014c3de475ad4c16a03aa0233c","last_date":"2026-06-04T00:29:28+02:00","last_author":"Shaun Roselt"},
  {"path":"people/3/data/changes.html","size":367,"last_commit":"8c820135e5f98c014c3de475ad4c16a03aa0233c","last_date":"2026-06-04T00:29:28+02:00","last_author":"Shaun Roselt"},
  {"path":"people/3/data/media.html","size":70,"last_commit":"8c820135e5f98c014c3de475ad4c16a03aa0233c","last_date":"2026-06-04T00:29:28+02:00","last_author":"Shaun Roselt"},
  {"path":"people/1/profile.html","size":1014,"last_commit":"de382cdc7e3cae92795dc0760cf8efd2ac6a38fe","last_date":"2026-06-07T18:53:28+02:00","last_author":"Shaun Roselt"},
  {"path":"people/1/data/profile.html","size":4768,"last_commit":"e7fa1ef7535c303059cb5490e5db33e40380fbfe","last_date":"2026-06-06T00:59:14+02:00","last_author":"Shaun Roselt"},
  {"path":"people/1/data/tree.html","size":69,"last_commit":"8c820135e5f98c014c3de475ad4c16a03aa0233c","last_date":"2026-06-04T00:29:28+02:00","last_author":"Shaun Roselt"},
  {"path":"people/1/data/talk.html","size":67,"last_commit":"8c820135e5f98c014c3de475ad4c16a03aa0233c","last_date":"2026-06-04T00:29:28+02:00","last_author":"Shaun Roselt"},
  {"path":"people/1/data/changes.html","size":367,"last_commit":"8c820135e5f98c014c3de475ad4c16a03aa0233c","last_date":"2026-06-04T00:29:28+02:00","last_author":"Shaun Roselt"},
  {"path":"people/1/data/media.html","size":70,"last_commit":"8c820135e5f98c014c3de475ad4c16a03aa0233c","last_date":"2026-06-04T00:29:28+02:00","last_author":"Shaun Roselt"},
  {"path":"people/24/profile.html","size":1013,"last_commit":"de382cdc7e3cae92795dc0760cf8efd2ac6a38fe","last_date":"2026-06-07T18:53:28+02:00","last_author":"Shaun Roselt"},
  {"path":"people/24/data/profile.html","size":885,"last_commit":"e7fa1ef7535c303059cb5490e5db33e40380fbfe","last_date":"2026-06-06T00:59:14+02:00","last_author":"Shaun Roselt"},
  {"path":"people/24/data/tree.html","size":69,"last_commit":"b56c7c69bf3f8e0b023e91b853e14e2e44db9d49","last_date":"2026-06-04T12:39:21+02:00","last_author":"Shaun Roselt"},
  {"path":"people/24/data/talk.html","size":67,"last_commit":"b56c7c69bf3f8e0b023e91b853e14e2e44db9d49","last_date":"2026-06-04T12:39:21+02:00","last_author":"Shaun Roselt"},
  {"path":"people/24/data/changes.html","size":124,"last_commit":"b56c7c69bf3f8e0b023e91b853e14e2e44db9d49","last_date":"2026-06-04T12:39:21+02:00","last_author":"Shaun Roselt"},
  {"path":"people/24/data/media.html","size":70,"last_commit":"b56c7c69bf3f8e0b023e91b853e14e2e44db9d49","last_date":"2026-06-04T12:39:21+02:00","last_author":"Shaun Roselt"},
  {"path":"people/19/profile.html","size":1027,"last_commit":"de382cdc7e3cae92795dc0760cf8efd2ac6a38fe","last_date":"2026-06-07T18:53:28+02:00","last_author":"Shaun Roselt"},
  {"path":"people/19/data/profile.html","size":1160,"last_commit":"e7fa1ef7535c303059cb5490e5db33e40380fbfe","last_date":"2026-06-06T00:59:14+02:00","last_author":"Shaun Roselt"},
  {"path":"people/19/data/tree.html","size":69,"last_commit":"b56c7c69bf3f8e0b023e91b853e14e2e44db9d49","last_date":"2026-06-04T12:39:21+02:00","last_author":"Shaun Roselt"},
  {"path":"people/19/data/talk.html","size":67,"last_commit":"b56c7c69bf3f8e0b023e91b853e14e2e44db9d49","last_date":"2026-06-04T12:39:21+02:00","last_author":"Shaun Roselt"},
  {"path":"people/19/data/changes.html","size":124,"last_commit":"b56c7c69bf3f8e0b023e91b853e14e2e44db9d49","last_date":"2026-06-04T12:39:21+02:00","last_author":"Shaun Roselt"},
  {"path":"people/19/data/media.html","size":70,"last_commit":"b56c7c69bf3f8e0b023e91b853e14e2e44db9d49","last_date":"2026-06-04T12:39:21+02:00","last_author":"Shaun Roselt"},
  {"path":"people/22/profile.html","size":1024,"last_commit":"de382cdc7e3cae92795dc0760cf8efd2ac6a38fe","last_date":"2026-06-07T18:53:28+02:00","last_author":"Shaun Roselt"},
  {"path":"people/22/data/profile.html","size":859,"last_commit":"e7fa1ef7535c303059cb5490e5db33e40380fbfe","last_date":"2026-06-06T00:59:14+02:00","last_author":"Shaun Roselt"},
  {"path":"people/22/data/tree.html","size":69,"last_commit":"b56c7c69bf3f8e0b023e91b853e14e2e44db9d49","last_date":"2026-06-04T12:39:21+02:00","last_author":"Shaun Roselt"},
  {"path":"people/22/data/talk.html","size":67,"last_commit":"b56c7c69bf3f8e0b023e91b853e14e2e44db9d49","last_date":"2026-06-04T12:39:21+02:00","last_author":"Shaun Roselt"},
  {"path":"people/22/data/changes.html","size":124,"last_commit":"b56c7c69bf3f8e0b023e91b853e14e2e44db9d49","last_date":"2026-06-04T12:39:21+02:00","last_author":"Shaun Roselt"},
  {"path":"people/22/data/media.html","size":70,"last_commit":"b56c7c69bf3f8e0b023e91b853e14e2e44db9d49","last_date":"2026-06-04T12:39:21+02:00","last_author":"Shaun Roselt"},
  {"path":"people/8/profile.html","size":1018,"last_commit":"de382cdc7e3cae92795dc0760cf8efd2ac6a38fe","last_date":"2026-06-07T18:53:28+02:00","last_author":"Shaun Roselt"},
  {"path":"people/8/data/profile.html","size":1335,"last_commit":"07a3081c76e20caf38ae87987328171a644d2571","last_date":"2026-06-07T17:40:16+02:00","last_author":"Shaun Roselt"},
  {"path":"people/8/data/tree.html","size":69,"last_commit":"d8a9adb58da2f3a8c8002cccb2944c0423fc9c3e","last_date":"2026-06-07T16:00:57+02:00","last_author":"Shaun Roselt"},
  {"path":"people/8/data/talk.html","size":67,"last_commit":"d8a9adb58da2f3a8c8002cccb2944c0423fc9c3e","last_date":"2026-06-07T16:00:57+02:00","last_author":"Shaun Roselt"},
  {"path":"people/8/data/changes.html","size":367,"last_commit":"d8a9adb58da2f3a8c8002cccb2944c0423fc9c3e","last_date":"2026-06-07T16:00:57+02:00","last_author":"Shaun Roselt"},
  {"path":"people/8/data/media.html","size":70,"last_commit":"d8a9adb58da2f3a8c8002cccb2944c0423fc9c3e","last_date":"2026-06-07T16:00:57+02:00","last_author":"Shaun Roselt"},
  {"path":"people/10/profile.html","size":1015,"last_commit":"de382cdc7e3cae92795dc0760cf8efd2ac6a38fe","last_date":"2026-06-07T18:53:28+02:00","last_author":"Shaun Roselt"},
  {"path":"people/10/data/profile.html","size":1331,"last_commit":"d8a9adb58da2f3a8c8002cccb2944c0423fc9c3e","last_date":"2026-06-07T16:00:57+02:00","last_author":"Shaun Roselt"},
  {"path":"people/10/data/tree.html","size":69,"last_commit":"d8a9adb58da2f3a8c8002cccb2944c0423fc9c3e","last_date":"2026-06-07T16:00:57+02:00","last_author":"Shaun Roselt"},
  {"path":"people/10/data/talk.html","size":67,"last_commit":"d8a9adb58da2f3a8c8002cccb2944c0423fc9c3e","last_date":"2026-06-07T16:00:57+02:00","last_author":"Shaun Roselt"},
  {"path":"people/10/data/changes.html","size":367,"last_commit":"d8a9adb58da2f3a8c8002cccb2944c0423fc9c3e","last_date":"2026-06-07T16:00:57+02:00","last_author":"Shaun Roselt"},
  {"path":"people/10/data/media.html","size":70,"last_commit":"d8a9adb58da2f3a8c8002cccb2944c0423fc9c3e","last_date":"2026-06-07T16:00:57+02:00","last_author":"Shaun Roselt"},
  {"path":"people/18/profile.html","size":1023,"last_commit":"de382cdc7e3cae92795dc0760cf8efd2ac6a38fe","last_date":"2026-06-07T18:53:28+02:00","last_author":"Shaun Roselt"},
  {"path":"people/18/data/profile.html","size":1146,"last_commit":"e7fa1ef7535c303059cb5490e5db33e40380fbfe","last_date":"2026-06-06T00:59:14+02:00","last_author":"Shaun Roselt"},
  {"path":"people/18/data/tree.html","size":69,"last_commit":"b56c7c69bf3f8e0b023e91b853e14e2e44db9d49","last_date":"2026-06-04T12:39:21+02:00","last_author":"Shaun Roselt"},
  {"path":"people/18/data/talk.html","size":67,"last_commit":"b56c7c69bf3f8e0b023e91b853e14e2e44db9d49","last_date":"2026-06-04T12:39:21+02:00","last_author":"Shaun Roselt"},
  {"path":"people/18/data/changes.html","size":124,"last_commit":"b56c7c69bf3f8e0b023e91b853e14e2e44db9d49","last_date":"2026-06-04T12:39:21+02:00","last_author":"Shaun Roselt"},
  {"path":"people/18/data/media.html","size":70,"last_commit":"b56c7c69bf3f8e0b023e91b853e14e2e44db9d49","last_date":"2026-06-04T12:39:21+02:00","last_author":"Shaun Roselt"},
  {"path":"people/index.html","size":7376,"last_commit":"de382cdc7e3cae92795dc0760cf8efd2ac6a38fe","last_date":"2026-06-07T18:53:28+02:00","last_author":"Shaun Roselt"},
  {"path":"people/11/profile.html","size":1011,"last_commit":"de382cdc7e3cae92795dc0760cf8efd2ac6a38fe","last_date":"2026-06-07T18:53:28+02:00","last_author":"Shaun Roselt"},
  {"path":"people/11/data/profile.html","size":11184,"last_commit":"1383896eba070ac3e26d517e4f42b9d085bdff11","last_date":"2026-06-07T16:55:12+02:00","last_author":"Shaun Roselt"},
  {"path":"people/11/data/tree.html","size":69,"last_commit":"1383896eba070ac3e26d517e4f42b9d085bdff11","last_date":"2026-06-07T16:55:12+02:00","last_author":"Shaun Roselt"},
  {"path":"people/11/data/talk.html","size":67,"last_commit":"1383896eba070ac3e26d517e4f42b9d085bdff11","last_date":"2026-06-07T16:55:12+02:00","last_author":"Shaun Roselt"},
  {"path":"people/11/data/profile-table.html","size":1086,"last_commit":"1383896eba070ac3e26d517e4f42b9d085bdff11","last_date":"2026-06-07T16:55:12+02:00","last_author":"Shaun Roselt"},
  {"path":"people/11/data/changes.html","size":145,"last_commit":"1383896eba070ac3e26d517e4f42b9d085bdff11","last_date":"2026-06-07T16:55:12+02:00","last_author":"Shaun Roselt"},
  {"path":"people/11/data/media.html","size":70,"last_commit":"1383896eba070ac3e26d517e4f42b9d085bdff11","last_date":"2026-06-07T16:55:12+02:00","last_author":"Shaun Roselt"},
  {"path":"components/app-search.js","size":26110,"last_commit":"a840a4b55a8081611dd72763442cc977418b8957","last_date":"2026-06-07T18:32:30+02:00","last_author":"Shaun Roselt"},
  {"path":"components/people-page-profile-table.js","size":3870,"last_commit":"8c820135e5f98c014c3de475ad4c16a03aa0233c","last_date":"2026-06-04T00:29:28+02:00","last_author":"Shaun Roselt"},
  {"path":"components/people-page.js","size":23171,"last_commit":"a840a4b55a8081611dd72763442cc977418b8957","last_date":"2026-06-07T18:32:30+02:00","last_author":"Shaun Roselt"},
  {"path":"index.js","size":4908,"last_commit":"e7fa1ef7535c303059cb5490e5db33e40380fbfe","last_date":"2026-06-06T00:59:14+02:00","last_author":"Shaun Roselt"},
  {"path":"pages/privacy_policy.html","size":3998,"last_commit":"de382cdc7e3cae92795dc0760cf8efd2ac6a38fe","last_date":"2026-06-07T18:53:28+02:00","last_author":"Shaun Roselt"},
  {"path":"pages/settings.html","size":9019,"last_commit":"de382cdc7e3cae92795dc0760cf8efd2ac6a38fe","last_date":"2026-06-07T18:53:28+02:00","last_author":"Shaun Roselt"},
  {"path":"pages/statistics.html","size":26477,"last_commit":"d8a9adb58da2f3a8c8002cccb2944c0423fc9c3e","last_date":"2026-06-07T16:00:57+02:00","last_author":"Shaun Roselt"},
  {"path":"pages/contact.html","size":2173,"last_commit":"de382cdc7e3cae92795dc0760cf8efd2ac6a38fe","last_date":"2026-06-07T18:53:28+02:00","last_author":"Shaun Roselt"},
  {"path":"pages/notifications.html","size":1916,"last_commit":"de382cdc7e3cae92795dc0760cf8efd2ac6a38fe","last_date":"2026-06-07T18:53:28+02:00","last_author":"Shaun Roselt"},
  {"path":"pages/home.html","size":6664,"last_commit":"de382cdc7e3cae92795dc0760cf8efd2ac6a38fe","last_date":"2026-06-07T18:53:28+02:00","last_author":"Shaun Roselt"},
  {"path":"pages/search.html","size":2710,"last_commit":"de382cdc7e3cae92795dc0760cf8efd2ac6a38fe","last_date":"2026-06-07T18:53:28+02:00","last_author":"Shaun Roselt"},
  {"path":"pages/terms_of_use.html","size":4738,"last_commit":"de382cdc7e3cae92795dc0760cf8efd2ac6a38fe","last_date":"2026-06-07T18:53:28+02:00","last_author":"Shaun Roselt"},
  {"path":"pages/404.html","size":4758,"last_commit":"d8a9adb58da2f3a8c8002cccb2944c0423fc9c3e","last_date":"2026-06-07T16:00:57+02:00","last_author":"Shaun Roselt"},
  {"path":"data/themes/light.css","size":0,"last_commit":"2f9cb56dd009bca24e432974d0c3dab3c9ab8b46","last_date":"2026-05-27T21:15:10+02:00","last_author":"Shaun Roselt"},
  {"path":"data/themes/dark.css","size":0,"last_commit":"2f9cb56dd009bca24e432974d0c3dab3c9ab8b46","last_date":"2026-05-27T21:15:10+02:00","last_author":"Shaun Roselt"},
  {"path":"data/themes/themes.js","size":0,"last_commit":"2f9cb56dd009bca24e432974d0c3dab3c9ab8b46","last_date":"2026-05-27T21:15:10+02:00","last_author":"Shaun Roselt"},
  {"path":"data/languages/languages.js","size":0,"last_commit":"2f9cb56dd009bca24e432974d0c3dab3c9ab8b46","last_date":"2026-05-27T21:15:10+02:00","last_author":"Shaun Roselt"},
  {"path":"tree-test-1/index.js","size":48089,"last_commit":"e7fa1ef7535c303059cb5490e5db33e40380fbfe","last_date":"2026-06-06T00:59:14+02:00","last_author":"Shaun Roselt"},
  {"path":"tree-test-1/index.css","size":11270,"last_commit":"f4c7a57fe368af3bf8414297f1cf061a9ea818aa","last_date":"2026-06-06T00:05:34+02:00","last_author":"Shaun Roselt"},
  {"path":"tree-test-1/index.html","size":3276,"last_commit":"d55c87a9d0fb0280225a1beca091e09e6017625f","last_date":"2026-06-06T00:05:34+02:00","last_author":"Shaun Roselt"},
  {"path":"site-info.js","size":12593,"last_commit":"de382cdc7e3cae92795dc0760cf8efd2ac6a38fe","last_date":"2026-06-07T18:53:28+02:00","last_author":"Shaun Roselt"},
  {"path":"lib/Web-Framework/components/action-button.js","size":4206,"last_commit":"","last_date":"","last_author":""},
  {"path":"lib/Web-Framework/components/full-header.js","size":62356,"last_commit":"","last_date":"","last_author":""},
  {"path":"lib/Web-Framework/components/full-page-toolbar.js","size":25406,"last_commit":"","last_date":"","last_author":""},
  {"path":"lib/Web-Framework/components/mini-header.js","size":10119,"last_commit":"","last_date":"","last_author":""},
  {"path":"lib/Web-Framework/components/mini-footer.js","size":3721,"last_commit":"","last_date":"","last_author":""},
  {"path":"lib/Web-Framework/components/full-footer.js","size":14779,"last_commit":"","last_date":"","last_author":""},
  {"path":"lib/Web-Framework/components/sister-projects.js","size":10844,"last_commit":"","last_date":"","last_author":""},
  {"path":"lib/Web-Framework/styles/common.css","size":43685,"last_commit":"","last_date":"","last_author":""},
  {"path":"lib/Web-Framework/styles/portal-index.css","size":80794,"last_commit":"","last_date":"","last_author":""},
  {"path":"lib/Web-Framework/site-runtime.js","size":4908,"last_commit":"","last_date":"","last_author":""},
  {"path":"lib/Web-Framework/site-info.js","size":13300,"last_commit":"","last_date":"","last_author":""},
  {"path":"lib/people-registry.js","size":1832,"last_commit":"9b9726427a34426916a3a3322b89c0d1663cf6e6","last_date":"2026-06-07T16:35:08+02:00","last_author":"Shaun Roselt"},
  {"path":"lib/notifications.js","size":3064,"last_commit":"e7fa1ef7535c303059cb5490e5db33e40380fbfe","last_date":"2026-06-06T00:59:14+02:00","last_author":"Shaun Roselt"},
  {"path":"lib/routing.js","size":0,"last_commit":"8c820135e5f98c014c3de475ad4c16a03aa0233c","last_date":"2026-06-04T00:29:28+02:00","last_author":"Shaun Roselt"},
  {"path":"lib/download-manager.js","size":13314,"last_commit":"e7fa1ef7535c303059cb5490e5db33e40380fbfe","last_date":"2026-06-06T00:59:14+02:00","last_author":"Shaun Roselt"},
  {"path":"404.html","size":4752,"last_commit":"d8a9adb58da2f3a8c8002cccb2944c0423fc9c3e","last_date":"2026-06-07T16:00:57+02:00","last_author":"Shaun Roselt"},
  {"path":"index.html","size":53419,"last_commit":"de382cdc7e3cae92795dc0760cf8efd2ac6a38fe","last_date":"2026-06-07T18:53:28+02:00","last_author":"Shaun Roselt"}
]
